core/__init__.py
core/admin.py
core/apps.py
core/fields.py
core/forms.py
core/models.py
core/requirements.txt
core/settings.py
core/tests.py
core/urls.py
core/validators.py
core/views.py
core/management/__init__.py
core/management/commands/__init__.py
core/management/commands/build.py
core/management/commands/snippets/api_router.txt
core/management/commands/snippets/api_router_urls.txt
core/management/commands/snippets/api_urls.txt
core/management/commands/snippets/api_view.txt
core/management/commands/snippets/createtemplate.txt
core/management/commands/snippets/crud_urls.txt
core/management/commands/snippets/crud_views.txt
core/management/commands/snippets/deletetemplate.txt
core/management/commands/snippets/detailtemplate.txt
core/management/commands/snippets/form.txt
core/management/commands/snippets/form_urls.txt
core/management/commands/snippets/listtemplate.txt
core/management/commands/snippets/modal_form.txt
core/management/commands/snippets/serializer.txt
core/management/commands/snippets/serializer_urls.txt
core/management/commands/snippets/updatetemplate.txt
core/management/commands/snippets/url.txt
core/management/commands/snippets/url_imports.txt
core/migrations/0001_initial.py
core/migrations/0002_parameterforbase_url_integracao.py
core/migrations/__init__.py
core/static/bootstrap4/css/bootstrap-grid.css
core/static/bootstrap4/css/bootstrap-grid.css.map
core/static/bootstrap4/css/bootstrap-grid.min.css
core/static/bootstrap4/css/bootstrap-grid.min.css.map
core/static/bootstrap4/css/bootstrap-reboot.css
core/static/bootstrap4/css/bootstrap-reboot.css.map
core/static/bootstrap4/css/bootstrap-reboot.min.css
core/static/bootstrap4/css/bootstrap-reboot.min.css.map
core/static/bootstrap4/css/bootstrap.css
core/static/bootstrap4/css/bootstrap.css.map
core/static/bootstrap4/css/bootstrap.min.css
core/static/bootstrap4/css/bootstrap.min.css.map
core/static/bootstrap4/js/bootstrap.js
core/static/bootstrap4/js/bootstrap.min.js
boilerplate_manager-1.0.1.dev0.dist-info/AUTHORS.md
boilerplate_manager-1.0.1.dev0.dist-info/LICENSE
boilerplate_manager-1.0.1.dev0.dist-info/METADATA
boilerplate_manager-1.0.1.dev0.dist-info/WHEEL
boilerplate_manager-1.0.1.dev0.dist-info/top_level.txt
boilerplate_manager-1.0.1.dev0.dist-info/RECORD
