Metadata-Version: 2.1
Name: boilerplate-manager
Version: 1.0.1.dev0
Summary: It is a Django app to generate forms, templates, Api Rest and views for apps of your project.
Home-page: https://github.com/agencia-tecnologia-palmas/boilerplate-manager.git
Author: Agência Municipal de Tecnologia da Informação do Município de Palmas
Author-email: dev.licencas@palmas.to.gov.br
License: MIT License
Platform: UNKNOWN
Classifier: Development Status :: 5 - Production/Stable
Classifier: Environment :: Web Environment
Classifier: Framework :: Django
Classifier: Framework :: Django :: 2.1
Classifier: Intended Audience :: Developers
Classifier: License :: OSI Approved :: MIT License
Classifier: Operating System :: OS Independent
Classifier: Programming Language :: Python
Classifier: Programming Language :: Python :: 3.5
Classifier: Programming Language :: Python :: 3.6
Classifier: Topic :: Internet :: WWW/HTTP
Classifier: Topic :: Internet :: WWW/HTTP :: Dynamic Content
Requires-Dist: django (>=2.1)
Requires-Dist: django-cors-headers (>=2.4.0)
Requires-Dist: djangorestframework (>=3.8.2)
Requires-Dist: requests (>=2.19.1)
